<annotation>
	<folder>EZwerge</folder>
	<filename>pic060.jpg</filename>
	<path>C:\Users\u162248\Downloads\EZwerge\pic060.jpg</path>
	<source>
		<database>Unknown</database>
	</source>
	<size>
		<width>800</width>
		<height>600</height>
		<depth>3</depth>
	</size>
	<segmented>0</segmented>
	<object>
		<name>Fahrt</name>
		<pose>Unspecified</pose>
		<truncated>0</truncated>
		<difficult>0</difficult>
		<bndbox>
			<xmin>393</xmin>
			<ymin>225</ymin>
			<xmax>464</xmax>
			<ymax>306</ymax>
		</bndbox>
	</object>
</annotation>
